.coveragerc
.gitignore
.travis.yml
LICENSE.rst
README.md
pyproject.toml
readme_classification_after_contour.png
readme_classification_after_mean_variance.png
readme_classification_before_contour.png
readme_classification_before_mean_variance.png
readme_grad.png
readme_nplan.png
readme_objective.png
readme_regression_after.png
readme_regression_before.png
requirements.txt
setup.py
.github/workflows/CI.yml
.github/workflows/publish.yml
examples/classification.py
examples/regression.py
probit/__init__.py
probit/_version.py
probit/approximators.py
probit/utilities.py
probit.egg-info/PKG-INFO
probit.egg-info/SOURCES.txt
probit.egg-info/dependency_links.txt
probit.egg-info/requires.txt
probit.egg-info/top_level.txt
probit/implicit/Laplace.py
probit/implicit/VB.py
probit/implicit/solvers.py
probit/test/__init__.py
probit/test/test_implicit.py