Metadata-Version: 2.1
Name: probit
Version: 0.0.2
Summary: probit is a simple and accessible Gaussian process implementation in Jax
Home-page: https://github.com/bb515/probit
Author: Benjamin Boys, Toby Boyne, Ieronymos Maxoutis
License: MIT
Requires-Python: >=3.8
Requires-Dist: numpy
Requires-Dist: scipy
Requires-Dist: jaxopt>=0.5.5
Requires-Dist: backends>=1.4.32
Requires-Dist: mlkernels>=0.3.6
